group_action/__init__.py
group_action/burnside.py
group_action/conjugacy_classes.py
group_action/library.py
group_action/orbit.py
group_action/orbit_random.py
group_action/orbits.py
group_action/powerset.py
group_action/symmetric_functions.py
group_action-0.2.18.dist-info/LICENSE
group_action-0.2.18.dist-info/METADATA
group_action-0.2.18.dist-info/WHEEL
group_action-0.2.18.dist-info/entry_points.txt
group_action-0.2.18.dist-info/top_level.txt
group_action-0.2.18.dist-info/RECORD
