Metadata-Version: 2.1
Name: group-action
Version: 0.2.18
Summary: A Python package for group action.
Home-page: https://github.com/ant1sir/group_action
Author: ant1sir
Author-email: antoine@sirianni.ai
License: UNKNOWN
Platform: UNKNOWN
Classifier: Programming Language :: Python :: 3
Classifier: License :: OSI Approved :: MIT License
Classifier: Operating System :: OS Independent
Requires-Python: >=3.10
License-File: LICENSE
Requires-Dist: joblib (>=1.4.2)
Requires-Dist: tqdm (>=4.66.4)
